{"title":"超星尔雅刷课神器1-2(挂后台)","slug":"Tools/chaoxing-2","date":"2018-04-23T11:52:32.593Z","updated":"2018-04-23T11:52:43.460Z","comments":true,"path":"api/articles/Tools/chaoxing-2.json","photos":[],"link":"","excerpt":"上次那个的环境都是应该配置好的，这次来秀一个有点技术的吧，让你的女神爱上你，她选择是对的。","covers":null,"content":"<p>上次那个的环境都是应该配置好的，这次来秀一个有点技术的吧，让你的女神爱上你，她选择是对的。</p>\n<a id=\"more\"></a>\n<h2 id=\"biubiubiu\"><a href=\"#biubiubiu\" class=\"headerlink\" title=\"biubiubiu\"></a>biubiubiu</h2><p>不想说话，给链接，里面有教程<br>链接: <a href=\"https://pan.baidu.com/s/1bm4BA0Tb_UdJu--NF04c1g\" target=\"_blank\" rel=\"noopener\">https://pan.baidu.com/s/1bm4BA0Tb_UdJu--NF04c1g</a> 密码: eqam</p>\n","categories":[],"tags":[{"name":"Tools,超星尔雅","slug":"Tools-超星尔雅","count":2,"path":"api/tags/Tools-超星尔雅.json"}]}